flask_pypendency/__init__.py
Flask_Pypendency-0.1.0.dist-info/LICENSE
Flask_Pypendency-0.1.0.dist-info/METADATA
Flask_Pypendency-0.1.0.dist-info/WHEEL
Flask_Pypendency-0.1.0.dist-info/top_level.txt
Flask_Pypendency-0.1.0.dist-info/RECORD
