Metadata-Version: 2.1
Name: Flask-Pypendency
Version: 0.1.0
Summary: Flask extension for Pypendency, a dependency injection tool
Home-page: https://github.com/miguelgf/pypendency-flask
Author: Miguel González Flores
Author-email: miguelgzflores@gmail.com
License: MIT License
Platform: any
Classifier: Environment :: Web Environment
Classifier: Intended Audience :: Developers
Classifier: License :: OSI Approved :: MIT License
Classifier: Operating System :: OS Independent
Classifier: Programming Language :: Python
Classifier: Programming Language :: Python :: 3.6
Classifier: Programming Language :: Python :: 3.7
Classifier: Programming Language :: Python :: 3.8
Classifier: Topic :: Software Development :: Libraries
Classifier: Topic :: Software Development :: Libraries :: Python Modules
Classifier: Typing :: Typed
Classifier: Framework :: Flask
Requires-Python: >=3.6
Requires-Dist: Flask
Requires-Dist: Pypendency
